FractalTools/__init__.py
FractalTools-0.0.7.dist-info/LICENSE
FractalTools-0.0.7.dist-info/METADATA
FractalTools-0.0.7.dist-info/WHEEL
FractalTools-0.0.7.dist-info/top_level.txt
FractalTools-0.0.7.dist-info/RECORD
